jsnDB/__init__.py
jsnDB/json_database.py
jsnDB-1.0.2.dist-info/METADATA
jsnDB-1.0.2.dist-info/WHEEL
jsnDB-1.0.2.dist-info/top_level.txt
jsnDB-1.0.2.dist-info/RECORD
