Metadata-Version: 2.1
Name: jsnDB
Version: 1.0.2
Summary: A lightweight JSON-based database.
Classifier: Programming Language :: Python :: 3
Classifier: License :: OSI Approved :: MIT License
Classifier: Operating System :: OS Independent
Requires-Python: >=3.6
